README.rst
setup.py
PyRecs.egg-info/PKG-INFO
PyRecs.egg-info/SOURCES.txt
PyRecs.egg-info/dependency_links.txt
PyRecs.egg-info/requires.txt
PyRecs.egg-info/top_level.txt
pyrecs/__init__.py
pyrecs/collab.py