Metadata-Version: 1.0
Name: PyRecs
Version: 0.11
Summary: Recommender systems for Python
Home-page: https://github.com/ssaamm/PyRecs
Author: Samuel Taylor
Author-email: pip@samueltaylor.org
License: MIT
Platform: UNKNOWN
